setup.py
digRegexExtractor/__init__.py
digRegexExtractor/regex_extractor.py
digRegexExtractor.egg-info/PKG-INFO
digRegexExtractor.egg-info/SOURCES.txt
digRegexExtractor.egg-info/dependency_links.txt
digRegexExtractor.egg-info/requires.txt
digRegexExtractor.egg-info/top_level.txt
test/test_name_regex_extractor.py