Metadata-Version: 1.1
Name: digRegexExtractor
Version: 0.3.0
Summary: digRegexExtractor
Home-page: https://github.com/usc-isi-i2/dig-regex-extractor
Author: Jason Slepicka
Author-email: jasonslepicka@gmail.com
License: UNKNOWN
Download-URL: https://github.com/usc-isi-i2/dig-regex-extractor
Platform: UNKNOWN
